.gitignore
.gitlab-ci.yml
README.md
jenkinsPreBuildScript.sh
setup.py
bin/lbschedulerclient
bin/lbschedulermanager
lbCVMFSscheduler/__init__.py
lbCVMFSscheduler.egg-info/PKG-INFO
lbCVMFSscheduler.egg-info/SOURCES.txt
lbCVMFSscheduler.egg-info/dependency_links.txt
lbCVMFSscheduler.egg-info/requires.txt
lbCVMFSscheduler.egg-info/top_level.txt
lbCVMFSscheduler/lbCVMFSexecutor/LbCVMFSExecuter.py
lbCVMFSscheduler/lbCVMFSexecutor/LbCVMFSLogger.py
lbCVMFSscheduler/lbCVMFSexecutor/LbCVMFSManager.py
lbCVMFSscheduler/lbCVMFSexecutor/LbCVMFSScheduler.py
lbCVMFSscheduler/lbCVMFSexecutor/LbCVMFSStats.py
lbCVMFSscheduler/lbCVMFSexecutor/LockManager.py
lbCVMFSscheduler/lbCVMFSexecutor/MonitoringGW.py
lbCVMFSscheduler/lbCVMFSexecutor/__init__.py
lbCVMFSscheduler/lbscheduler/LbSchedulerClient.py
lbCVMFSscheduler/lbscheduler/LbSchedulerExecuter.py
lbCVMFSscheduler/lbscheduler/__init__.py