Metadata-Version: 1.1
Name: lbCVMFSscheduler
Version: 1.0.11
Summary: LHCb CVMFS scheduler
Home-page: https://gitlab.cern.ch/lhcb-core/lb-cvmfs-scheduler/
Author: CERN - LHCb Core Software
Author-email: lhcb-core-soft@cern.ch
License: GPL
Keywords: LHCb
Platform: UNKNOWN
Classifier: Development Status :: 3 - Alpha
Classifier: License :: OSI Approved :: GNU General Public License v3 (GPLv3)
Classifier: Programming Language :: Python :: 2.6
Classifier: Programming Language :: Python :: 2.7
Classifier: Programming Language :: Python :: 3.5
